hydra_cache/__init__.py
hydra_cache/mixins.py
hydra_cache/utils/__init__.py
hydra_cache/utils/cache.py
hydra_cache/utils/hasher.py
hydra_cache-0.1.2.dist-info/LICENSE
hydra_cache-0.1.2.dist-info/METADATA
hydra_cache-0.1.2.dist-info/WHEEL
hydra_cache-0.1.2.dist-info/top_level.txt
hydra_cache-0.1.2.dist-info/RECORD
