Metadata-Version: 2.1
Name: hydra_cache
Version: 0.1.2
Summary: A mixin that unleash the Kraken of DJANGO Caching Power
Home-page: https://github.com/iamharshdev/hydra_cache
Author: Harsh Vardhan Goswami
Author-email: me@iamharsh.dev
Classifier: Development Status :: 3 - Alpha
Classifier: Intended Audience :: Developers
Classifier: License :: OSI Approved :: MIT License
Classifier: Programming Language :: Python :: 3
Classifier: Programming Language :: Python :: 3.6
Classifier: Programming Language :: Python :: 3.7
Classifier: Programming Language :: Python :: 3.8
Classifier: Programming Language :: Python :: 3.9
Classifier: Framework :: Django
Requires-Python: >=3.6
License-File: LICENSE
Requires-Dist: Django >=4.2.10
